slack_messages.py
slack_messages/__init__.py
slack_messages/slack.py
slack_messages-0.0.2.dist-info/LICENSE
slack_messages-0.0.2.dist-info/METADATA
slack_messages-0.0.2.dist-info/WHEEL
slack_messages-0.0.2.dist-info/top_level.txt
slack_messages-0.0.2.dist-info/RECORD
