Metadata-Version: 2.1
Name: slack-messages
Version: 0.0.2
Summary: Slack messages made easy. Send slack messages to channels from you backend api etc.
Home-page: https://github.com/joegasewicz/slack-messages
Author: Joe Gasewicz
Author-email: joegasewicz@gmail.com
License: UNKNOWN
Platform: UNKNOWN
Classifier: Programming Language :: Python :: 3.7
Classifier: Programming Language :: Python :: 3.8
Classifier: Programming Language :: Python :: 3.9
Classifier: License :: OSI Approved :: GNU General Public License v3 or later (GPLv3+)
Classifier: Operating System :: OS Independent
Requires-Dist: requests
